restcraft-0.1.4.dist-info/METADATA
restcraft-0.1.4.dist-info/WHEEL
restcraft-0.1.4.dist-info/entry_points.txt
restcraft-0.1.4.dist-info/licenses/LICENSE
restcraft/__init__.py
restcraft/__version__.py
restcraft/contrib/__init__.py
restcraft/contrib/http/__init__.py
restcraft/contrib/http/multipart.py
restcraft/contrib/plugins/__init__.py
restcraft/contrib/plugins/cors_plugin.py
restcraft/exceptions.py
restcraft/http/__init__.py
restcraft/http/cookie.py
restcraft/http/request.py
restcraft/http/response.py
restcraft/http/router.py
restcraft/plugin.py
restcraft/py.typed
restcraft/restcraft.py
restcraft/utils/__init__.py
restcraft/utils/make_fields.py
restcraft/utils/metadata.py
restcraft/views.py
restcraft-0.1.4.dist-info/RECORD
