Metadata-Version: 2.1
Name: restcraft
Version: 0.1.4
Summary: A minimalist Python WSGI framework for building RESTful APIs.
Keywords: wsgi,framework,rest,api
Author-Email: Lucas Santana <lsfratel@gmail.com>
License: MIT
Classifier: Development Status :: 3 - Alpha
Classifier: Operating System :: OS Independent
Classifier: Intended Audience :: Developers
Classifier: License :: OSI Approved :: MIT License
Classifier: Topic :: Internet :: WWW/HTTP :: Dynamic Content :: CGI Tools/Libraries
Classifier: Topic :: Internet :: WWW/HTTP :: HTTP Servers
Classifier: Topic :: Internet :: WWW/HTTP :: WSGI
Classifier: Topic :: Internet :: WWW/HTTP :: WSGI :: Application
Classifier: Topic :: Internet :: WWW/HTTP :: WSGI :: Middleware
Classifier: Topic :: Internet :: WWW/HTTP :: WSGI :: Server
Classifier: Topic :: Software Development :: Libraries :: Application Frameworks
Classifier: Programming Language :: Python :: 3
Project-URL: source, https://github.com/lsfratel/restcraft
Requires-Python: >=3.10
